uldlib/__init__.py
uldlib/captcha.py
uldlib/cmd.py
uldlib/const.py
uldlib/downloader.py
uldlib/frontend.py
uldlib/linkcache.py
uldlib/model.tflite
uldlib/page.py
uldlib/part.py
uldlib/segfile.py
uldlib/torrunner.py
uldlib/utils.py
ulozto_downloader-3.5.2.dist-info/AUTHORS.md
ulozto_downloader-3.5.2.dist-info/LICENSE.txt
ulozto_downloader-3.5.2.dist-info/METADATA
ulozto_downloader-3.5.2.dist-info/WHEEL
ulozto_downloader-3.5.2.dist-info/entry_points.txt
ulozto_downloader-3.5.2.dist-info/top_level.txt
ulozto_downloader-3.5.2.dist-info/RECORD
