Metadata-Version: 2.1
Name: ulozto-downloader
Version: 3.5.2
Summary: Uloz.to quick multiple sessions downloader.
Home-page: https://github.com/setnicka/ulozto-downloader
Author: Jiří Setnička and Vlado Driver
Author-email: setnicka@seznam.cz
License: MIT
Classifier: License :: OSI Approved :: MIT License
Classifier: Programming Language :: Python :: 3
Requires-Python: >=3.7
License-File: LICENSE.txt
License-File: AUTHORS.md
Requires-Dist: requests
Requires-Dist: Pillow
Requires-Dist: ansicolors
Requires-Dist: colorama >=0.4.6
Requires-Dist: numpy
Requires-Dist: pysocks
Requires-Dist: stem
Requires-Dist: cloudscraper
Provides-Extra: auto-captcha
Requires-Dist: tflite-runtime ; (python_version < "3.10") and extra == 'auto-captcha'
Requires-Dist: tensorflow ; (python_version >= "3.10") and extra == 'auto-captcha'
